indextts/__init__.py
indextts/cli.py
indextts/infer.py
indextts/infer_v2.py
indextts/BigVGAN/ECAPA_TDNN.py
indextts/BigVGAN/__init__.py
indextts/BigVGAN/activations.py
indextts/BigVGAN/bigvgan.py
indextts/BigVGAN/models.py
indextts/BigVGAN/utils.py
indextts/BigVGAN/alias_free_activation/__init__.py
indextts/BigVGAN/alias_free_activation/cuda/.gitignore
indextts/BigVGAN/alias_free_activation/cuda/__init__.py
indextts/BigVGAN/alias_free_activation/cuda/activation1d.py
indextts/BigVGAN/alias_free_activation/cuda/anti_alias_activation.cpp
indextts/BigVGAN/alias_free_activation/cuda/anti_alias_activation_cuda.cu
indextts/BigVGAN/alias_free_activation/cuda/compat.h
indextts/BigVGAN/alias_free_activation/cuda/load.py
indextts/BigVGAN/alias_free_activation/cuda/type_shim.h
indextts/BigVGAN/alias_free_activation/torch/__init__.py
indextts/BigVGAN/alias_free_activation/torch/act.py
indextts/BigVGAN/alias_free_activation/torch/filter.py
indextts/BigVGAN/alias_free_activation/torch/resample.py
indextts/BigVGAN/alias_free_torch/__init__.py
indextts/BigVGAN/alias_free_torch/act.py
indextts/BigVGAN/alias_free_torch/filter.py
indextts/BigVGAN/alias_free_torch/resample.py
indextts/BigVGAN/nnet/CNN.py
indextts/BigVGAN/nnet/__init__.py
indextts/BigVGAN/nnet/linear.py
indextts/BigVGAN/nnet/normalization.py
indextts/gpt/__init__.py
indextts/gpt/conformer_encoder.py
indextts/gpt/model.py
indextts/gpt/model_v2.py
indextts/gpt/perceiver.py
indextts/gpt/transformers_beam_search.py
indextts/gpt/transformers_generation_utils.py
indextts/gpt/transformers_gpt2.py
indextts/gpt/transformers_modeling_utils.py
indextts/gpt/conformer/__init__.py
indextts/gpt/conformer/attention.py
indextts/gpt/conformer/embedding.py
indextts/gpt/conformer/subsampling.py
indextts/s2mel/hf_utils.py
indextts/s2mel/optimizers.py
indextts/s2mel/wav2vecbert_extract.py
indextts/s2mel/dac/__init__.py
indextts/s2mel/dac/__main__.py
indextts/s2mel/dac/model/__init__.py
indextts/s2mel/dac/model/base.py
tts_webui_index_tts-2.0.0.dist-info/METADATA
tts_webui_index_tts-2.0.0.dist-info/WHEEL
tts_webui_index_tts-2.0.0.dist-info/entry_points.txt
tts_webui_index_tts-2.0.0.dist-info/licenses/LICENSE
tts_webui_index_tts-2.0.0.dist-info/licenses/LICENSE_ZH.txt
tts_webui_index_tts-2.0.0.dist-info/RECORD
