Metadata-Version: 2.4
Name: tts-webui.index-tts
Version: 2.0.0
Summary: IndexTTS2: A Breakthrough in Emotionally Expressive and Duration-Controlled Auto-Regressive Zero-Shot Text-to-Speech
Project-URL: Homepage, https://github.com/index-tts/index-tts
Project-URL: Repository, https://github.com/index-tts/index-tts.git
Author: Bilibili IndexTTS Team
License-Expression: LicenseRef-Bilibili-IndexTTS
License-File: LICENSE
License-File: LICENSE_ZH.txt
Classifier: Development Status :: 5 - Production/Stable
Classifier: Intended Audience :: Developers
Classifier: Intended Audience :: Science/Research
Classifier: Natural Language :: Chinese (Simplified)
Classifier: Natural Language :: English
Classifier: Operating System :: OS Independent
Classifier: Programming Language :: Python :: 3
Classifier: Topic :: Scientific/Engineering
Classifier: Topic :: Scientific/Engineering :: Artificial Intelligence
Requires-Python: >=3.10
Requires-Dist: accelerate>=1.8.1
Requires-Dist: descript-audiotools>=0.7.2
Requires-Dist: einops>=0.8.1
Requires-Dist: json5>=0.10.0
Requires-Dist: librosa>=0.10.0
Requires-Dist: matplotlib<4,>=3.6.0
Requires-Dist: modelscope>=1.20.0
Requires-Dist: munch>=4.0.0
Requires-Dist: numpy<2,>=1.20
Requires-Dist: omegaconf>=2.3.0
Requires-Dist: pandas<3,>=1.5
Requires-Dist: safetensors>=0.5.2
Requires-Dist: sentencepiece>=0.2.1
Requires-Dist: textstat>=0.7.10
Requires-Dist: torch>=2.1.1
Requires-Dist: torchaudio>=2.1.1
Requires-Dist: tqdm>=4.67.1
Requires-Dist: transformers==4.52.1
Requires-Dist: wetext>=0.0.9; sys_platform != 'linux'
Requires-Dist: wetextprocessing; sys_platform == 'linux'
Provides-Extra: deepspeed
Requires-Dist: deepspeed==0.17.1; extra == 'deepspeed'
Provides-Extra: webui
Requires-Dist: gradio==5.45.0; extra == 'webui'
